autoassistant/README.md
autoassistant/autoassistant.py
autoassistant/config.py
autoassistant/config.py_bk
autoassistant/health_check.py
autoassistant/requirements.txt
autoassistant-0.5.dist-info/METADATA
autoassistant-0.5.dist-info/WHEEL
autoassistant-0.5.dist-info/entry_points.txt
autoassistant-0.5.dist-info/top_level.txt
autoassistant-0.5.dist-info/RECORD
